{"nodes": [{"id": "refactoring_candidates", "label": "Refactor Candidates List", "file_type": "document", "source_file": "tdd/refactoring.md", "source_location": null, "source_url": null, "captured_at": null, "author": null, "contributor": null}, {"id": "refactoring_duplication", "label": "Extract Duplication", "file_type": "document", "source_file": "tdd/refactoring.md", "source_location": "Line 5", "source_url": null, "captured_at": null, "author": null, "contributor": null}, {"id": "refactoring_shallow_module_combine", "label": "Combine/Deepen Shallow Modules", "file_type": "document", "source_file": "tdd/refactoring.md", "source_location": "Line 7", "source_url": null, "captured_at": null, "author": null, "contributor": null}, {"id": "refactoring_feature_envy", "label": "Move Logic Where Data Lives (Feature Envy)", "file_type": "document", "source_file": "tdd/refactoring.md", "source_location": "Line 8", "source_url": null, "captured_at": null, "author": null, "contributor": null}, {"id": "refactoring_primitive_obsession", "label": "Introduce Value Objects (Primitive Obsession)", "file_type": "document", "source_file": "tdd/refactoring.md", "source_location": "Line 9", "source_url": null, "captured_at": null, "author": null, "contributor": null}], "edges": [{"source": "refactoring_shallow_module_combine", "target": "deepmodules_deep_module", "relation": "references", "confidence": "INFERRED", "confidence_score": 0.85, "source_file": "tdd/refactoring.md", "source_location": "Line 7", "weight": 1.0}, {"source": "refactoring_shallow_module_combine", "target": "deepmodules_shallow_module", "relation": "references", "confidence": "INFERRED", "confidence_score": 0.85, "source_file": "tdd/refactoring.md", "source_location": "Line 7", "weight": 1.0}, {"source": "refactoring_candidates", "target": "refactoring_duplication", "relation": "references", "confidence": "EXTRACTED", "confidence_score": 1.0, "source_file": "tdd/refactoring.md", "source_location": "Line 5", "weight": 1.0}, {"source": "refactoring_candidates", "target": "refactoring_shallow_module_combine", "relation": "references", "confidence": "EXTRACTED", "confidence_score": 1.0, "source_file": "tdd/refactoring.md", "source_location": "Line 7", "weight": 1.0}, {"source": "refactoring_candidates", "target": "refactoring_feature_envy", "relation": "references", "confidence": "EXTRACTED", "confidence_score": 1.0, "source_file": "tdd/refactoring.md", "source_location": "Line 8", "weight": 1.0}, {"source": "refactoring_candidates", "target": "refactoring_primitive_obsession", "relation": "references", "confidence": "EXTRACTED", "confidence_score": 1.0, "source_file": "tdd/refactoring.md", "source_location": "Line 9", "weight": 1.0}], "hyperedges": []}